LICENSE
PYPI.rst
README.rst
setup.py
stereosite/__init__.py
stereosite/degene.py
stereosite/scii.py
stereosite/scii_tensor.py
stereosite/tf_infer.py
stereosite.egg-info/PKG-INFO
stereosite.egg-info/SOURCES.txt
stereosite.egg-info/dependency_links.txt
stereosite.egg-info/requires.txt
stereosite.egg-info/top_level.txt
stereosite/cn/__init__.py
stereosite/cn/cellneighbor.py
stereosite/cn/deconvolution.py
stereosite/plot/__init__.py
stereosite/plot/cellneighbor.py
stereosite/plot/intensity.py
stereosite/plot/mask.py
stereosite/plot/net.py
stereosite/plot/sankey.py
stereosite/plot/scii.py
stereosite/plot/scii_circos.py
stereosite/plot/scii_net.py
stereosite/plot/scii_tensor.py
stereosite/ppi/__init__.py
stereosite/ppi/ppi_analysis.py
stereosite/ppi/query.py
stereosite/read/__init__.py
stereosite/read/gem.py