Metadata-Version: 2.1
Name: stereosite
Version: 2.2.1
Summary: Analysis spatial transcriptomics data
Home-page: https://github.com/STOmics/StereoSiTE
Author: LiuXing
Author-email: liuxing2@genomics.cn
License: GPL-3 License
Keywords: spatial cell interaction intensity
Platform: any
License-File: LICENSE
Requires-Dist: anndata>=0.8.0
Requires-Dist: scanpy>=1.9.1
Requires-Dist: squidpy>=1.1.2
Requires-Dist: decoupler>=1.4.0
Requires-Dist: pydeseq2>=0.3.6
Requires-Dist: networkx>=3.1
Requires-Dist: tensorly>=0.8.1
Requires-Dist: scikit-learn>=1.2.1
Requires-Dist: torch>=1.11.0
Requires-Dist: igraph>=0.10.4
Requires-Dist: pycirclize>=1.1.0
Requires-Dist: cell2location==0.1.3
